pytest_funparam/__init__.py
pytest_funparam/py.typed
pytest_funparam-0.3.0.dist-info/entry_points.txt
pytest_funparam-0.3.0.dist-info/LICENSE
pytest_funparam-0.3.0.dist-info/WHEEL
pytest_funparam-0.3.0.dist-info/METADATA
pytest_funparam-0.3.0.dist-info/RECORD
