Metadata-Version: 2.1
Name: pytest-funparam
Version: 0.3.0
Summary: An alternative way to parametrize test cases.
Author-email: "Ryan J. Miller" <rjmiller10@gmail.com>
Maintainer-email: "Ryan J. Miller" <rjmiller10@gmail.com>
Requires-Python: >=3.6
Classifier: Development Status :: 4 - Beta
Classifier: Framework :: Pytest
Classifier: Intended Audience :: Developers
Classifier: Topic :: Software Development :: Testing
Classifier: Programming Language :: Python
Classifier: Programming Language :: Python :: 3
Classifier: Programming Language :: Python :: 3.6
Classifier: Programming Language :: Python :: 3.7
Classifier: Programming Language :: Python :: 3.8
Classifier: Programming Language :: Python :: 3.9
Classifier: Programming Language :: Python :: 3 :: Only
Classifier: Programming Language :: Python :: Implementation :: CPython
Classifier: Operating System :: OS Independent
Classifier: License :: OSI Approved :: MIT License
Requires-Dist: pytest >=4.6.0
Project-URL: homepage, https://github.com/rjmill/pytest-funparam
